teammate/__init__.py
teammate-0.0.0.dist-info/METADATA
teammate-0.0.0.dist-info/WHEEL
teammate-0.0.0.dist-info/top_level.txt
teammate-0.0.0.dist-info/RECORD
